odoo/addons/bc3_importer/README.rst
odoo/addons/bc3_importer/__init__.py
odoo/addons/bc3_importer/__manifest__.py
odoo/addons/bc3_importer/data/bc3_version_data.xml
odoo/addons/bc3_importer/data/product_data.xml
odoo/addons/bc3_importer/data/uom_data.xml
odoo/addons/bc3_importer/i18n/bc3_importer.pot
odoo/addons/bc3_importer/i18n/es.po
odoo/addons/bc3_importer/models/__init__.py
odoo/addons/bc3_importer/models/bc3_version.py
odoo/addons/bc3_importer/models/sale_order.py
odoo/addons/bc3_importer/readme/CONTRIBUTORS.rst
odoo/addons/bc3_importer/readme/DESCRIPTION.rst
odoo/addons/bc3_importer/security/bc3_file_security.xml
odoo/addons/bc3_importer/security/ir.model.access.csv
odoo/addons/bc3_importer/static/description/icon.png
odoo/addons/bc3_importer/static/description/index.html
odoo/addons/bc3_importer/tests/__init__.py
odoo/addons/bc3_importer/tests/bc3_file_test.bc3
odoo/addons/bc3_importer/tests/test_bc3_import_wizard.py
odoo/addons/bc3_importer/tests/test_bc3_version.py
odoo/addons/bc3_importer/views/bc3_version_views.xml
odoo/addons/bc3_importer/views/sale_order_views.xml
odoo/addons/bc3_importer/wizard/__init__.py
odoo/addons/bc3_importer/wizard/bc3_import_wizard.py
odoo/addons/bc3_importer/wizard/bc3_import_wizard_views.xml
odoo14_addon_bc3_importer-14.0.1.0.0.dist-info/METADATA
odoo14_addon_bc3_importer-14.0.1.0.0.dist-info/WHEEL
odoo14_addon_bc3_importer-14.0.1.0.0.dist-info/top_level.txt
odoo14_addon_bc3_importer-14.0.1.0.0.dist-info/RECORD
