Metadata-Version: 2.1
Name: odoo14-addon-bc3_importer
Version: 14.0.1.0.0
Summary: BC3 files importer
Home-page: https://github.com/OCA/vertical-construction
Author: Binhex, Odoo Community Association (OCA)
Author-email: support@odoo-community.org
License: AGPL-3
Classifier: Programming Language :: Python
Classifier: Framework :: Odoo
Classifier: Framework :: Odoo :: 14.0
Classifier: License :: OSI Approved :: GNU Affero General Public License v3
Requires-Python: >=3.6
Requires-Dist: chardet
Requires-Dist: iteration-utilities
Requires-Dist: odoo <14.1dev,>=14.0a
